equos/__init__.py
equos/apis/agent_api.py
equos/apis/agent_async_api.py
equos/apis/avatar_api.py
equos/apis/avatar_async_api.py
equos/apis/session_api.py
equos/apis/session_async_api.py
equos/equos.py
equos/models/agent_models.py
equos/models/avatar_models.py
equos/models/error_models.py
equos/models/session_models.py
equos/py.typed
equos/utils/async_http_utils.py
equos/utils/constants_utils.py
equos/utils/http_utils.py
equos-1.2.4.dist-info/METADATA
equos-1.2.4.dist-info/WHEEL
equos-1.2.4.dist-info/RECORD
