Metadata-Version: 2.4
Name: equos
Version: 1.2.4
Summary: Equos.ai official Python SDK.
Author: Loïc Combis
Author-email: loic@equos.ai
Requires-Python: >=3.11
Classifier: Programming Language :: Python :: 3
Classifier: Programming Language :: Python :: 3.11
Classifier: Programming Language :: Python :: 3.12
Classifier: Programming Language :: Python :: 3.13
Classifier: Programming Language :: Python :: 3.14
Requires-Dist: dotenv (>=0.9.9,<0.10.0)
Requires-Dist: httpx (>=0.28.1,<0.29.0)
Requires-Dist: pydantic (>=2.11.9,<3.0.0)
Requires-Dist: requests (>=2.32.5,<3.0.0)
